<?xml version="1.0" encoding="UTF-8"?>
<node id="ResourceTypeGenres" label="DNB 2019-11-07">
  <isComposedBy>
    <node id="ID001" label="Allgemeines, Informationswissenschaft">
    <hasNote></hasNote>
      <isComposedBy>
        <node id="ID002" label="000 Allgemeines, Wissenschaft">
        <hasNote></hasNote>
        </node>
        <node id="ID003" label="004 Informatik">
        <hasNote></hasNote>
        </node>
        <node id="ID004" label="010 Bibliographien">
        <hasNote></hasNote>
        </node>
        <node id="ID005" label="020 Bibliotheks- und Informationswissenschaft">
        <hasNote></hasNote>
        </node>
        <node id="ID006" label="030 Enzyklopädien">
        <hasNote></hasNote>
        </node>
        <node id="ID007" label="050 Zeitschriften, forlaufende Sammelwerke">
        <hasNote></hasNote>
        </node>
        <node id="ID008" label="060 Organisation, Museumswirtschaft">
        <hasNote></hasNote>
        </node>
        <node id="ID009" label="070 Nachrichtenmedien, Journalismus, Verlagswesen">
        <hasNote></hasNote>
        </node>
        <node id="ID010" label="080 Allgemein Sammelwerke">
        <hasNote></hasNote>
        </node>
      </isComposedBy>
    </node>
    <node id="ID011" label="Philosophie und Psychologie">
    <hasNote></hasNote>
      <isComposedBy>
        <node id="ID012" label="100 Philosophie">
        <hasNote></hasNote>
        </node>
        <node id="ID013" label="130 Parapsychologie, Okkultismus">
        <hasNote></hasNote>
        </node>
        <node id="ID014" label="150 Psychologie">
        <hasNote></hasNote>
        </node>
      </isComposedBy>
    </node>
    <node id="ID015" label="Religion">
    <hasNote></hasNote>
      <isComposedBy>
        <node id="ID016" label="200 Religion, Religionsphilosophie">
        <hasNote></hasNote>
        </node>
        <node id="ID017" label="220 Bibel">
        <hasNote></hasNote>
        </node>
        <node id="ID018" label="230 Theologie, Christentum">
        <hasNote></hasNote>
        </node>
        <node id="ID019" label="290 Andere Religionen">
        <hasNote></hasNote>
        </node>
      </isComposedBy>
    </node>
    <node id="ID020" label="Sozialwissenschaften">
    <hasNote></hasNote>
      <isComposedBy>
        <node id="ID021" label="300 Sozialwissenschaften, Soziologie, Anthropologie">
        <hasNote></hasNote>
        </node>
        <node id="ID022" label="310 Statistik">
        <hasNote></hasNote>
        </node>
        <node id="ID023" label="320 Politik">
        <hasNote></hasNote>
        </node>
        <node id="ID024" label="330 Wirtschaft">
        <hasNote></hasNote>
        </node>
        <node id="ID025" label="333.7 Natürliche Ressourcen, Energie, Umwelt">
        <hasNote></hasNote>
        </node>
        <node id="ID026" label="340 Recht">
        <hasNote></hasNote>
        </node>
        <node id="ID027" label="350 Öffentliche Verwaltung">
        <hasNote></hasNote>
        </node>
        <node id="ID028" label="360 Soziale Probleme, Sozialdienste, Versicherungen">
        <hasNote></hasNote>
        </node>
        <node id="ID029" label="370 Erziehung, Schul- und Bildungswesen">
        <hasNote></hasNote>
        </node>
        <node id="ID030" label="380 Handel, Kommunikation, Verkehr">
        <hasNote></hasNote>
        </node>
        <node id="ID031" label="390 Bräuche, Etikette, Folklore">
        <hasNote></hasNote>
        </node>
      </isComposedBy>
    </node>
    <node id="ID032" label="Sprache">
    <hasNote></hasNote>
      <isComposedBy>
        <node id="ID033" label="400 Sprache, Linguistik">
        <hasNote></hasNote>
        </node>
        <node id="ID034" label="420 Englisch">
        <hasNote></hasNote>
        </node>
        <node id="ID035" label="430 Deutsch">
        <hasNote></hasNote>
        </node>
        <node id="ID036" label="439 Andere germanische Sprachen">
        <hasNote></hasNote>
        </node>
        <node id="ID037" label="440 Französisch, romanische Sprachen allgemein">
        <hasNote></hasNote>
        </node>
        <node id="ID038" label="450 Italienisch, Rumänisch, Rätoromanisch">
        <hasNote></hasNote>
        </node>
        <node id="ID039" label="460 Spanisch, Portugiesisch">
        <hasNote></hasNote>
        </node>
        <node id="ID040" label="470 Latein">
        <hasNote></hasNote>
        </node>
        <node id="ID041" label="480 Griechisch">
        <hasNote></hasNote>
        </node>
        <node id="ID042" label="490 Andere Sprachen">
        <hasNote></hasNote>
        </node>
        <node id="ID043" label="491.8 Slawische Sprachen">
        <hasNote></hasNote>
        </node>
      </isComposedBy>
    </node>
    <node id="ID044" label="Naturwissenschaften und Mathematik">
    <hasNote></hasNote>
      <isComposedBy>
        <node id="ID045" label="500 Naturwissenschaften">
        <hasNote></hasNote>
        </node>
        <node id="ID046" label="510 Mathematik">
        <hasNote></hasNote>
        </node>
        <node id="ID047" label="520 Astronomie, Kartographie">
        <hasNote></hasNote>
        </node>
        <node id="ID048" label="530 Physik">
        <hasNote></hasNote>
        </node>
        <node id="ID049" label="540 Chemie">
        <hasNote></hasNote>
        </node>
        <node id="ID050" label="550 Geowissenschaften">
        <hasNote></hasNote>
        </node>
        <node id="ID051" label="560 Paläontologie">
        <hasNote></hasNote>
        </node>
        <node id="ID052" label="570 Biowissenschaften, Biologie">
        <hasNote></hasNote>
        </node>
        <node id="ID053" label="580 Pflanzen (Botanik)">
        <hasNote></hasNote>
        </node>
        <node id="ID054" label="590 Tiere (Zoologie)">
        <hasNote></hasNote>
        </node>
      </isComposedBy>
    </node>
    <node id="ID055" label="Technik, Medizin, angewandte Wissenschaft">
    <hasNote></hasNote>
      <isComposedBy>
        <node id="ID056" label="600 Technik">
        <hasNote></hasNote>
        </node>
        <node id="ID057" label="610 Medizin, Gesundheit, Ernährung">
        <hasNote></hasNote>
        </node>
        <node id="ID058" label="620 Ingenieurwissenschaften und Maschinenbau">
        <hasNote></hasNote>
        </node>
        <node id="ID059" label="621.3 Elektrotechnik, Elektronik">
        <hasNote></hasNote>
        </node>
        <node id="ID060" label="624 Ingenieurbau und Umwelttechnik">
        <hasNote></hasNote>
        </node>
        <node id="ID061" label="630 Landwirtschaft, Veterinärmedizin">
        <hasNote></hasNote>
        </node>
        <node id="ID062" label="631 Hauswirtschaft und Familienleben">
        <hasNote></hasNote>
        </node>
        <node id="ID063" label="650 Management">
        <hasNote></hasNote>
        </node>
        <node id="ID064" label="660 Technische Chemie">
        <hasNote></hasNote>
        </node>
        <node id="ID065" label="670 Industrielle und handwerkliche Fertigung">
        <hasNote></hasNote>
        </node>
        <node id="ID066" label="690 Hausbau, Bauhandwerk">
        <hasNote></hasNote>
        </node>
      </isComposedBy>
    </node>
    <node id="ID067" label="Künste und Unterhaltung">
    <hasNote></hasNote>
      <isComposedBy>
        <node id="ID068" label="700 Künste, Bildende Künste allgemein">
        <hasNote></hasNote>
        </node>
        <node id="ID069" label="710 Landschaftsgestaltung, Raumplanung">
        <hasNote></hasNote>
        </node>
        <node id="ID070" label="720 Architektur">
        <hasNote></hasNote>
        </node>
        <node id="ID071" label="730 Plastik, Numismatik, Keramik, Metallkunst">
        <hasNote></hasNote>
        </node>
        <node id="ID072" label="740 Grafik, angewandte Kunst">
        <hasNote></hasNote>
        </node>
        <node id="ID073" label="740.1 Comics, Cartoons, Karikaturen">
        <hasNote></hasNote>
        </node>
        <node id="ID074" label="750 Malerei">
        <hasNote></hasNote>
        </node>
        <node id="ID075" label="760 Druckgrafik, Drucke">
        <hasNote></hasNote>
        </node>
        <node id="ID076" label="770 Fotografie, Video, Computerkunst">
        <hasNote></hasNote>
        </node>
        <node id="ID077" label="780 Musik">
        <hasNote></hasNote>
        </node>
        <node id="ID078" label="790 Freizeitgestaltung, Darstellende Kunst">
        <hasNote></hasNote>
        </node>
        <node id="ID079" label="791 Öffentliche Darbietungen, Film, Rundfunk">
        <hasNote></hasNote>
        </node>
        <node id="ID080" label="792 Theater, Tanz">
        <hasNote></hasNote>
        </node>
        <node id="ID081" label="793 Spiel">
        <hasNote></hasNote>
        </node>
        <node id="ID082" label="796 Sport">
        <hasNote></hasNote>
        </node>
      </isComposedBy>
    </node>
    <node id="ID083" label="Literatur">
    <hasNote></hasNote>
      <isComposedBy>
        <node id="ID084" label="800 Literatur, Rhetorik, Literaturwissenschaft">
        <hasNote></hasNote>
        </node>
        <node id="ID085" label="810 Englische Literatur Amerikas">
        <hasNote></hasNote>
        </node>
        <node id="ID086" label="820 Englische Literatur">
        <hasNote></hasNote>
        </node>
        <node id="ID087" label="830 Deutsche Literatur">
        <hasNote></hasNote>
        </node>
        <node id="ID088" label="840 Literatur in anderen germanischen Sprachen">
        <hasNote></hasNote>
        </node>
        <node id="ID089" label="850 Italienische, rumänische, rätoromanische Literatur">
        <hasNote></hasNote>
        </node>
        <node id="ID090" label="860 Spanische und portugiesische Literatur">
        <hasNote></hasNote>
        </node>
        <node id="ID091" label="870 Lateinische Literatur">
        <hasNote></hasNote>
        </node>
        <node id="ID092" label="880 Griechische Literatur">
        <hasNote></hasNote>
        </node>
        <node id="ID093" label="890 Literatur in anderen Sprachen">
        <hasNote></hasNote>
        </node>
        <node id="ID094" label="891.8 Slawische Literatur">
        <hasNote></hasNote>
        </node>
      </isComposedBy>
    </node>
    <node id="ID095" label="Geschichte und Geografie">
    <hasNote></hasNote>
      <isComposedBy>
        <node id="ID096" label="900 Geschichte">
        <hasNote></hasNote>
        </node>
        <node id="ID097" label="910 Geografie, Reisen">
        <hasNote></hasNote>
        </node>
        <node id="ID098" label="914.3 Geografie, Reisen (Deutschland)">
        <hasNote></hasNote>
        </node>
        <node id="ID099" label="920 Biografie, Genealgie, Heraldik">
        <hasNote></hasNote>
        </node>
        <node id="ID100" label="930 Alte Geschivhte, Archäologie">
        <hasNote></hasNote>
        </node>
        <node id="ID101" label="940 Geschichte Europas">
        <hasNote></hasNote>
        </node>
        <node id="ID102" label="943 Geschichte Deutschlands">
        <hasNote></hasNote>
        </node>
        <node id="ID103" label="950 Geschichte Asiens">
        <hasNote></hasNote>
        </node>
        <node id="ID104" label="960 Geschichte Afrikas">
        <hasNote></hasNote>
        </node>
        <node id="ID105" label="970 Geschichte Nordamerikas">
        <hasNote></hasNote>
        </node>
        <node id="ID106" label="980 Geschichte Südamerikas">
        <hasNote></hasNote>
        </node>
        <node id="ID107" label="990 Geschichte der übrigen Welt">
        <hasNote></hasNote>
        </node>
      </isComposedBy>
    </node>
    <node id="ID108" label="Belletristik">
    <hasNote></hasNote>
    </node>
    <node id="ID109" label="Kinder- und Jugendliteratur">
    <hasNote></hasNote>
    </node>
    <node id="ID110" label="Schulbücher">
    <hasNote></hasNote>
    </node>
    <node id="ID111" label="Abgeschlossene Veröffentlichungen">
    <hasNote></hasNote>
    </node>
    <node id="ID112" label="Berichtigungen">
    <hasNote></hasNote>
    </node>
  </isComposedBy>
</node>
