<?xml version="1.0" encoding="UTF-8"?>
<node id="ResourceTypeGenres" label="COUNTRIES2 2021-09-20">
  <isComposedBy>
    <node id="Node1" label="Germany" selectable="false">
    <hasNote></hasNote>
      <isComposedBy>
        <node id="DE1" label="Germany - Baden-Württemberg" selectable="true">
        <hasNote></hasNote>
        </node>
        <node id="DE2" label="Germany - Bavaria" selectable="true">
        <hasNote></hasNote>
        </node>
        <node id="DE3" label="Germany - Berlin" selectable="true">
        <hasNote></hasNote>
        </node>
        <node id="DE4" label="Germany - Brandenburg" selectable="true">
        <hasNote></hasNote>
        </node>
        <node id="DE5" label="Germany - Bremen" selectable="true">
        <hasNote></hasNote>
        </node>
        <node id="DE6" label="Germany - Hamburg" selectable="true">
        <hasNote></hasNote>
        </node>
        <node id="DE7" label="Germany - Hesse" selectable="true">
        <hasNote></hasNote>
        </node>
        <node id="DE9" label="Germany - Lower Saxony" selectable="true">
        <hasNote></hasNote>
        </node>
        <node id="DE8" label="Germany - Mecklenburg-West Pomerania" selectable="true">
        <hasNote></hasNote>
        </node>
        <node id="DEA" label="Germany - North Rhine-Westphalia" selectable="true">
        <hasNote></hasNote>
        </node>
        <node id="DEB" label="Germany - Rhineland-Palatine" selectable="true">
        <hasNote></hasNote>
        </node>
        <node id="DEC" label="Germany - Saar" selectable="true">
        <hasNote></hasNote>
        </node>
        <node id="DED" label="Germany - Saxony" selectable="true">
        <hasNote></hasNote>
        </node>
        <node id="DEE" label="Germany - Saxony-Anhalt" selectable="true">
        <hasNote></hasNote>
        </node>
        <node id="DEF" label="Germany - Schleswig-Holstein" selectable="true">
        <hasNote></hasNote>
        </node>
        <node id="DEG" label="Germany - Thuringia" selectable="true">
        <hasNote></hasNote>
        </node>
      </isComposedBy>
    </node>
    <node id="Node2" label="Other countries (without Germany)" selectable="false">
    <hasNote></hasNote>
      <isComposedBy>
        <node id="AFG-individual" label="Afghanistan" selectable="true">
        <hasNote></hasNote>
        </node>
        <node id="ALA-individual" label="Åland Islands" selectable="true">
        <hasNote></hasNote>
        </node>
        <node id="ALB-individual" label="Albania" selectable="true">
        <hasNote></hasNote>
        </node>
        <node id="DZA-individual" label="Algeria" selectable="true">
        <hasNote></hasNote>
        </node>
        <node id="ASM-individual" label="American Samoa" selectable="true">
        <hasNote></hasNote>
        </node>
        <node id="AND-individual" label="Andorra" selectable="true">
        <hasNote></hasNote>
        </node>
        <node id="AGO-individual" label="Angola" selectable="true">
        <hasNote></hasNote>
        </node>
        <node id="AIA-individual" label="Anguilla" selectable="true">
        <hasNote></hasNote>
        </node>
        <node id="ATA-individual" label="Antarctica" selectable="true">
        <hasNote></hasNote>
        </node>
        <node id="ATG-individual" label="Antigua and Barbuda" selectable="true">
        <hasNote></hasNote>
        </node>
        <node id="ARG-individual" label="Argentina" selectable="true">
        <hasNote></hasNote>
        </node>
        <node id="ARM-individual" label="Armenia" selectable="true">
        <hasNote></hasNote>
        </node>
        <node id="ABW-individual" label="Aruba" selectable="true">
        <hasNote></hasNote>
        </node>
        <node id="AUS-individual" label="Australia" selectable="true">
        <hasNote></hasNote>
        </node>
        <node id="AUT-individual" label="Austria" selectable="true">
        <hasNote></hasNote>
        </node>
        <node id="AZE-individual" label="Azerbaijan" selectable="true">
        <hasNote></hasNote>
        </node>
        <node id="BHS-individual" label="Bahamas" selectable="true">
        <hasNote></hasNote>
        </node>
        <node id="BHR-individual" label="Bahrain" selectable="true">
        <hasNote></hasNote>
        </node>
        <node id="BGD-individual" label="Bangladesh" selectable="true">
        <hasNote></hasNote>
        </node>
        <node id="BRB-individual" label="Barbados" selectable="true">
        <hasNote></hasNote>
        </node>
        <node id="ATF1-individual" label="Bassas da India" selectable="true">
        <hasNote></hasNote>
        </node>
        <node id="BLR-individual" label="Belarus" selectable="true">
        <hasNote></hasNote>
        </node>
        <node id="BEL-individual" label="Belgium" selectable="true">
        <hasNote></hasNote>
        </node>
        <node id="BLZ-individual" label="Belize" selectable="true">
        <hasNote></hasNote>
        </node>
        <node id="BEN-individual" label="Benin" selectable="true">
        <hasNote></hasNote>
        </node>
        <node id="BMU-individual" label="Bermuda" selectable="true">
        <hasNote></hasNote>
        </node>
        <node id="BTN-individual" label="Bhutan" selectable="true">
        <hasNote></hasNote>
        </node>
        <node id="BOL-individual" label="Bolivia" selectable="true">
        <hasNote></hasNote>
        </node>
        <node id="BIH-individual" label="Bosnia and Herzegovina" selectable="true">
        <hasNote></hasNote>
        </node>
        <node id="BWA-individual" label="Botswana" selectable="true">
        <hasNote></hasNote>
        </node>
        <node id="BVT-individual" label="Bouvet Island" selectable="true">
        <hasNote></hasNote>
        </node>
        <node id="BRA-individual" label="Brazil" selectable="true">
        <hasNote></hasNote>
        </node>
        <node id="IOT-individual" label="British Indian Ocean Territory" selectable="true">
        <hasNote></hasNote>
        </node>
        <node id="BRN-individual" label="Brunei Darussalam" selectable="true">
        <hasNote></hasNote>
        </node>
        <node id="BGR-individual" label="Bulgaria" selectable="true">
        <hasNote></hasNote>
        </node>
        <node id="BFA-individual" label="Burkina Faso" selectable="true">
        <hasNote></hasNote>
        </node>
        <node id="BDI-individual" label="Burundi" selectable="true">
        <hasNote></hasNote>
        </node>
        <node id="KHM-individual" label="Cambodia" selectable="true">
        <hasNote></hasNote>
        </node>
        <node id="CMR-individual" label="Cameroon" selectable="true">
        <hasNote></hasNote>
        </node>
        <node id="CAN-individual" label="Canada" selectable="true">
        <hasNote></hasNote>
        </node>
        <node id="CPV-individual" label="Cape Verde" selectable="true">
        <hasNote></hasNote>
        </node>
        <node id="CYM-individual" label="Cayman Islands" selectable="true">
        <hasNote></hasNote>
        </node>
        <node id="CAF-individual" label="Central African Republic" selectable="true">
        <hasNote></hasNote>
        </node>
        <node id="TCD-individual" label="Chad" selectable="true">
        <hasNote></hasNote>
        </node>
        <node id="CHL-individual" label="Chile" selectable="true">
        <hasNote></hasNote>
        </node>
        <node id="CHN-individual" label="China" selectable="true">
        <hasNote></hasNote>
        </node>
        <node id="CXR-individual" label="Christmas Island" selectable="true">
        <hasNote></hasNote>
        </node>
        <node id="FRAU-individual" label="Clipperton" selectable="true">
        <hasNote></hasNote>
        </node>
        <node id="CCK-individual" label="Cocos (Keeling) Islands" selectable="true">
        <hasNote></hasNote>
        </node>
        <node id="COL-individual" label="Colombia" selectable="true">
        <hasNote></hasNote>
        </node>
        <node id="COM-individual" label="Comoros" selectable="true">
        <hasNote></hasNote>
        </node>
        <node id="COD-individual" label="Congo" selectable="true">
        <hasNote></hasNote>
        </node>
        <node id="COG-individual" label="Congo" selectable="true">
        <hasNote></hasNote>
        </node>
        <node id="COK-individual" label="Cook Islands" selectable="true">
        <hasNote></hasNote>
        </node>
        <node id="CRI-individual" label="Costa Rica" selectable="true">
        <hasNote></hasNote>
        </node>
        <node id="HRV-individual" label="Croatia" selectable="true">
        <hasNote></hasNote>
        </node>
        <node id="CUB-individual" label="Cuba" selectable="true">
        <hasNote></hasNote>
        </node>
        <node id="CYP-individual" label="Cyprus" selectable="true">
        <hasNote></hasNote>
        </node>
        <node id="CZE-individual" label="Czech Republic" selectable="true">
        <hasNote></hasNote>
        </node>
        <node id="CIV-individual" label="Côte d'Ivoire" selectable="true">
        <hasNote></hasNote>
        </node>
        <node id="DNK-individual" label="Denmark" selectable="true">
        <hasNote></hasNote>
        </node>
        <node id="DJI-individual" label="Djibouti" selectable="true">
        <hasNote></hasNote>
        </node>
        <node id="DMA-individual" label="Dominica" selectable="true">
        <hasNote></hasNote>
        </node>
        <node id="DOM-individual" label="Dominican Republic" selectable="true">
        <hasNote></hasNote>
        </node>
        <node id="ECU-individual" label="Ecuador" selectable="true">
        <hasNote></hasNote>
        </node>
        <node id="EGY-individual" label="Egypt" selectable="true">
        <hasNote></hasNote>
        </node>
        <node id="SLV-individual" label="El Salvador" selectable="true">
        <hasNote></hasNote>
        </node>
        <node id="GNQ-individual" label="Equatorial Guinea" selectable="true">
        <hasNote></hasNote>
        </node>
        <node id="ERI-individual" label="Eritrea" selectable="true">
        <hasNote></hasNote>
        </node>
        <node id="EST-individual" label="Estonia" selectable="true">
        <hasNote></hasNote>
        </node>
        <node id="ETH-individual" label="Ethiopia" selectable="true">
        <hasNote></hasNote>
        </node>
        <node id="FLK-individual" label="Falkland Islands (Malvinas)" selectable="true">
        <hasNote></hasNote>
        </node>
        <node id="FRO-individual" label="Faroe Islands" selectable="true">
        <hasNote></hasNote>
        </node>
        <node id="FJI-individual" label="Fiji" selectable="true">
        <hasNote></hasNote>
        </node>
        <node id="FIN-individual" label="Finland" selectable="true">
        <hasNote></hasNote>
        </node>
        <node id="FRA-individual" label="France" selectable="true">
        <hasNote></hasNote>
        </node>
        <node id="FXX-individual" label="France (metropolitan)" selectable="true">
        <hasNote></hasNote>
        </node>
        <node id="GUF-individual" label="French Guiana" selectable="true">
        <hasNote></hasNote>
        </node>
        <node id="PYF-individual" label="French Polynesia" selectable="true">
        <hasNote></hasNote>
        </node>
        <node id="ATF-individual" label="French Southern Territories" selectable="true">
        <hasNote></hasNote>
        </node>
        <node id="GAB-individual" label="Gabon" selectable="true">
        <hasNote></hasNote>
        </node>
        <node id="GMB-individual" label="Gambia" selectable="true">
        <hasNote></hasNote>
        </node>
        <node id="PSE1-individual" label="Gaza Strip" selectable="true">
        <hasNote></hasNote>
        </node>
        <node id="GEO-individual" label="Georgia" selectable="true">
        <hasNote></hasNote>
        </node>
        <node id="GHA-individual" label="Ghana" selectable="true">
        <hasNote></hasNote>
        </node>
        <node id="GIB-individual" label="Gibraltar" selectable="true">
        <hasNote></hasNote>
        </node>
        <node id="ATF2-individual" label="Glorioso Islands" selectable="true">
        <hasNote></hasNote>
        </node>
        <node id="GRC-individual" label="Greece" selectable="true">
        <hasNote></hasNote>
        </node>
        <node id="GRL-individual" label="Greenland" selectable="true">
        <hasNote></hasNote>
        </node>
        <node id="GRD-individual" label="Grenada" selectable="true">
        <hasNote></hasNote>
        </node>
        <node id="GLP-individual" label="Guadeloupe" selectable="true">
        <hasNote></hasNote>
        </node>
        <node id="GUM-individual" label="Guam" selectable="true">
        <hasNote></hasNote>
        </node>
        <node id="GTM-individual" label="Guatemala" selectable="true">
        <hasNote></hasNote>
        </node>
        <node id="GGY-individual" label="Guernsey" selectable="true">
        <hasNote></hasNote>
        </node>
        <node id="GIN-individual" label="Guinea" selectable="true">
        <hasNote></hasNote>
        </node>
        <node id="GNB-individual" label="Guinea-Bissau" selectable="true">
        <hasNote></hasNote>
        </node>
        <node id="GUY-individual" label="Guyana" selectable="true">
        <hasNote></hasNote>
        </node>
        <node id="HTI-individual" label="Haiti" selectable="true">
        <hasNote></hasNote>
        </node>
        <node id="HMD-individual" label="Heard Island and McDonald Islands" selectable="true">
        <hasNote></hasNote>
        </node>
        <node id="HND-individual" label="Honduras" selectable="true">
        <hasNote></hasNote>
        </node>
        <node id="HKG-individual" label="Hong Kong" selectable="true">
        <hasNote></hasNote>
        </node>
        <node id="HUN-individual" label="Hungary" selectable="true">
        <hasNote></hasNote>
        </node>
        <node id="ISL-individual" label="Iceland" selectable="true">
        <hasNote></hasNote>
        </node>
        <node id="IND-individual" label="India" selectable="true">
        <hasNote></hasNote>
        </node>
        <node id="IDN-individual" label="Indonesia" selectable="true">
        <hasNote></hasNote>
        </node>
        <node id="IRN-individual" label="Iran" selectable="true">
        <hasNote></hasNote>
        </node>
        <node id="IRQ-individual" label="Iraq" selectable="true">
        <hasNote></hasNote>
        </node>
        <node id="IRL-individual" label="Ireland" selectable="true">
        <hasNote></hasNote>
        </node>
        <node id="IMN-individual" label="Isle of Man" selectable="true">
        <hasNote></hasNote>
        </node>
        <node id="ISR-individual" label="Israel" selectable="true">
        <hasNote></hasNote>
        </node>
        <node id="ITA-individual" label="Italy" selectable="true">
        <hasNote></hasNote>
        </node>
        <node id="JAM-individual" label="Jamaica" selectable="true">
        <hasNote></hasNote>
        </node>
        <node id="JPN-individual" label="Japan" selectable="true">
        <hasNote></hasNote>
        </node>
        <node id="JEY-individual" label="Jersey" selectable="true">
        <hasNote></hasNote>
        </node>
        <node id="JOR-individual" label="Jordan" selectable="true">
        <hasNote></hasNote>
        </node>
        <node id="ATF3-individual" label="Juan de Nova Island" selectable="true">
        <hasNote></hasNote>
        </node>
        <node id="KAZ-individual" label="Kazakhstan" selectable="true">
        <hasNote></hasNote>
        </node>
        <node id="KEN-individual" label="Kenya" selectable="true">
        <hasNote></hasNote>
        </node>
        <node id="KIR-individual" label="Kiribati" selectable="true">
        <hasNote></hasNote>
        </node>
        <node id="KOR-individual" label="Korea" selectable="true">
        <hasNote></hasNote>
        </node>
        <node id="PRK-individual" label="Korea" selectable="true">
        <hasNote></hasNote>
        </node>
        <node id="KWT-individual" label="Kuwait" selectable="true">
        <hasNote></hasNote>
        </node>
        <node id="KGZ-individual" label="Kyrgyzstan" selectable="true">
        <hasNote></hasNote>
        </node>
        <node id="LAO-individual" label="Lao People's Democratic Republic" selectable="true">
        <hasNote></hasNote>
        </node>
        <node id="LVA-individual" label="Latvia" selectable="true">
        <hasNote></hasNote>
        </node>
        <node id="LBN-individual" label="Lebanon" selectable="true">
        <hasNote></hasNote>
        </node>
        <node id="LSO-individual" label="Lesotho" selectable="true">
        <hasNote></hasNote>
        </node>
        <node id="LBR-individual" label="Liberia" selectable="true">
        <hasNote></hasNote>
        </node>
        <node id="LBY-individual" label="Libyan Arab Jamahiriya" selectable="true">
        <hasNote></hasNote>
        </node>
        <node id="LIE-individual" label="Liechtenstein" selectable="true">
        <hasNote></hasNote>
        </node>
        <node id="LTU-individual" label="Lithuania" selectable="true">
        <hasNote></hasNote>
        </node>
        <node id="LUX-individual" label="Luxembourg" selectable="true">
        <hasNote></hasNote>
        </node>
        <node id="MAC-individual" label="Macao" selectable="true">
        <hasNote></hasNote>
        </node>
        <node id="MKD-individual" label="Macedonia" selectable="true">
        <hasNote></hasNote>
        </node>
        <node id="MDG-individual" label="Madagascar" selectable="true">
        <hasNote></hasNote>
        </node>
        <node id="MWI-individual" label="Malawi" selectable="true">
        <hasNote></hasNote>
        </node>
        <node id="MYS-individual" label="Malaysia" selectable="true">
        <hasNote></hasNote>
        </node>
        <node id="MDV-individual" label="Maldives" selectable="true">
        <hasNote></hasNote>
        </node>
        <node id="MLI-individual" label="Mali" selectable="true">
        <hasNote></hasNote>
        </node>
        <node id="MLT-individual" label="Malta" selectable="true">
        <hasNote></hasNote>
        </node>
        <node id="MHL-individual" label="Marshall Islands" selectable="true">
        <hasNote></hasNote>
        </node>
        <node id="MTQ-individual" label="Martinique" selectable="true">
        <hasNote></hasNote>
        </node>
        <node id="MRT-individual" label="Mauritania" selectable="true">
        <hasNote></hasNote>
        </node>
        <node id="MUS-individual" label="Mauritius" selectable="true">
        <hasNote></hasNote>
        </node>
        <node id="MYT-individual" label="Mayotte" selectable="true">
        <hasNote></hasNote>
        </node>
        <node id="MEX-individual" label="Mexico" selectable="true">
        <hasNote></hasNote>
        </node>
        <node id="FSM-individual" label="Micronesia" selectable="true">
        <hasNote></hasNote>
        </node>
        <node id="MDA-individual" label="Moldova" selectable="true">
        <hasNote></hasNote>
        </node>
        <node id="MCO-individual" label="Monaco" selectable="true">
        <hasNote></hasNote>
        </node>
        <node id="MNG-individual" label="Mongolia" selectable="true">
        <hasNote></hasNote>
        </node>
        <node id="MNE-individual" label="Montenegro" selectable="true">
        <hasNote></hasNote>
        </node>
        <node id="MSR-individual" label="Montserrat" selectable="true">
        <hasNote></hasNote>
        </node>
        <node id="MAR-individual" label="Morocco" selectable="true">
        <hasNote></hasNote>
        </node>
        <node id="MOZ-individual" label="Mozambique" selectable="true">
        <hasNote></hasNote>
        </node>
        <node id="MMR-individual" label="Myanmar" selectable="true">
        <hasNote></hasNote>
        </node>
        <node id="NAM-individual" label="Namibia" selectable="true">
        <hasNote></hasNote>
        </node>
        <node id="NRU-individual" label="Nauru" selectable="true">
        <hasNote></hasNote>
        </node>
        <node id="NPL-individual" label="Nepal" selectable="true">
        <hasNote></hasNote>
        </node>
        <node id="NLD-individual" label="Netherlands" selectable="true">
        <hasNote></hasNote>
        </node>
        <node id="ANT-individual" label="Netherlands Antilles" selectable="true">
        <hasNote></hasNote>
        </node>
        <node id="NCL-individual" label="New Caledonia" selectable="true">
        <hasNote></hasNote>
        </node>
        <node id="NZL-individual" label="New Zealand" selectable="true">
        <hasNote></hasNote>
        </node>
        <node id="NIC-individual" label="Nicaragua" selectable="true">
        <hasNote></hasNote>
        </node>
        <node id="NER-individual" label="Niger" selectable="true">
        <hasNote></hasNote>
        </node>
        <node id="NGA-individual" label="Nigeria" selectable="true">
        <hasNote></hasNote>
        </node>
        <node id="NIU-individual" label="Niue" selectable="true">
        <hasNote></hasNote>
        </node>
        <node id="NFK-individual" label="Norfolk Island" selectable="true">
        <hasNote></hasNote>
        </node>
        <node id="MNP-individual" label="Northern Mariana Islands" selectable="true">
        <hasNote></hasNote>
        </node>
        <node id="NOR-individual" label="Norway" selectable="true">
        <hasNote></hasNote>
        </node>
        <node id="OMN-individual" label="Oman" selectable="true">
        <hasNote></hasNote>
        </node>
        <node id="PAK-individual" label="Pakistan" selectable="true">
        <hasNote></hasNote>
        </node>
        <node id="PLW-individual" label="Palau" selectable="true">
        <hasNote></hasNote>
        </node>
        <node id="PSE-individual" label="Palestinian Territory" selectable="true">
        <hasNote></hasNote>
        </node>
        <node id="PAN-individual" label="Panama" selectable="true">
        <hasNote></hasNote>
        </node>
        <node id="PNG-individual" label="Papua New Guinea" selectable="true">
        <hasNote></hasNote>
        </node>
        <node id="PRY-individual" label="Paraguay" selectable="true">
        <hasNote></hasNote>
        </node>
        <node id="PER-individual" label="Peru" selectable="true">
        <hasNote></hasNote>
        </node>
        <node id="PHL-individual" label="Philippines" selectable="true">
        <hasNote></hasNote>
        </node>
        <node id="PCN-individual" label="Pitcairn" selectable="true">
        <hasNote></hasNote>
        </node>
        <node id="POL-individual" label="Poland" selectable="true">
        <hasNote></hasNote>
        </node>
        <node id="PRT-individual" label="Portugal" selectable="true">
        <hasNote></hasNote>
        </node>
        <node id="PRI-individual" label="Puerto Rico" selectable="true">
        <hasNote></hasNote>
        </node>
        <node id="QAT-individual" label="Qatar" selectable="true">
        <hasNote></hasNote>
        </node>
        <node id="ROU-individual" label="Romania" selectable="true">
        <hasNote></hasNote>
        </node>
        <node id="RUS-individual" label="Russian Federation" selectable="true">
        <hasNote></hasNote>
        </node>
        <node id="RWA-individual" label="Rwanda" selectable="true">
        <hasNote></hasNote>
        </node>
        <node id="REU-individual" label="Réunion" selectable="true">
        <hasNote></hasNote>
        </node>
        <node id="BLM-individual" label="Saint Barthélemy" selectable="true">
        <hasNote></hasNote>
        </node>
        <node id="SHN-individual" label="Saint Helena" selectable="true">
        <hasNote></hasNote>
        </node>
        <node id="KNA-individual" label="Saint Kitts and Nevis" selectable="true">
        <hasNote></hasNote>
        </node>
        <node id="LCA-individual" label="Saint Lucia" selectable="true">
        <hasNote></hasNote>
        </node>
        <node id="MAF-individual" label="Saint Martin (French part)" selectable="true">
        <hasNote></hasNote>
        </node>
        <node id="SPM-individual" label="Saint Pierre and Miquelon" selectable="true">
        <hasNote></hasNote>
        </node>
        <node id="VCT-individual" label="Saint Vincent and the Grenadines" selectable="true">
        <hasNote></hasNote>
        </node>
        <node id="WSM-individual" label="Samoa" selectable="true">
        <hasNote></hasNote>
        </node>
        <node id="SMR-individual" label="San Marino" selectable="true">
        <hasNote></hasNote>
        </node>
        <node id="STP-individual" label="Sao Tome and Principe" selectable="true">
        <hasNote></hasNote>
        </node>
        <node id="SAU-individual" label="Saudi Arabia" selectable="true">
        <hasNote></hasNote>
        </node>
        <node id="SEN-individual" label="Senegal" selectable="true">
        <hasNote></hasNote>
        </node>
        <node id="SRB-individual" label="Serbia" selectable="true">
        <hasNote></hasNote>
        </node>
        <node id="SYC-individual" label="Seychelles" selectable="true">
        <hasNote></hasNote>
        </node>
        <node id="SLE-individual" label="Sierra Leone" selectable="true">
        <hasNote></hasNote>
        </node>
        <node id="SGP-individual" label="Singapore" selectable="true">
        <hasNote></hasNote>
        </node>
        <node id="SVK-individual" label="Slovakia" selectable="true">
        <hasNote></hasNote>
        </node>
        <node id="SVN-individual" label="Slovenia" selectable="true">
        <hasNote></hasNote>
        </node>
        <node id="SLB-individual" label="Solomon Islands" selectable="true">
        <hasNote></hasNote>
        </node>
        <node id="SOM-individual" label="Somalia" selectable="true">
        <hasNote></hasNote>
        </node>
        <node id="ZAF-individual" label="South Africa" selectable="true">
        <hasNote></hasNote>
        </node>
        <node id="SGS-individual" label="South Georgia and the South Sandwich Islands" selectable="true">
        <hasNote></hasNote>
        </node>
        <node id="SSD-individual" label="South Sudan" selectable="true">
        <hasNote></hasNote>
        </node>
        <node id="ESP-individual" label="Spain" selectable="true">
        <hasNote></hasNote>
        </node>
        <node id="LKA-individual" label="Sri Lanka" selectable="true">
        <hasNote></hasNote>
        </node>
        <node id="SDN-individual" label="Sudan" selectable="true">
        <hasNote></hasNote>
        </node>
        <node id="SUR-individual" label="Suriname" selectable="true">
        <hasNote></hasNote>
        </node>
        <node id="SJM-individual" label="Svalbard and Jan Mayen" selectable="true">
        <hasNote></hasNote>
        </node>
        <node id="SWZ-individual" label="Swaziland" selectable="true">
        <hasNote></hasNote>
        </node>
        <node id="SWE-individual" label="Sweden" selectable="true">
        <hasNote></hasNote>
        </node>
        <node id="CHE-individual" label="Switzerland" selectable="true">
        <hasNote></hasNote>
        </node>
        <node id="SYR-individual" label="Syrian Arab Republic" selectable="true">
        <hasNote></hasNote>
        </node>
        <node id="TWN-individual" label="Taiwan" selectable="true">
        <hasNote></hasNote>
        </node>
        <node id="TJK-individual" label="Tajikistan" selectable="true">
        <hasNote></hasNote>
        </node>
        <node id="TZA-individual" label="Tanzania" selectable="true">
        <hasNote></hasNote>
        </node>
        <node id="THA-individual" label="Thailand" selectable="true">
        <hasNote></hasNote>
        </node>
        <node id="TLS-individual" label="Timor-Leste" selectable="true">
        <hasNote></hasNote>
        </node>
        <node id="TGO-individual" label="Togo" selectable="true">
        <hasNote></hasNote>
        </node>
        <node id="TKL-individual" label="Tokelau" selectable="true">
        <hasNote></hasNote>
        </node>
        <node id="TON-individual" label="Tonga" selectable="true">
        <hasNote></hasNote>
        </node>
        <node id="TTO-individual" label="Trinidad and Tobago" selectable="true">
        <hasNote></hasNote>
        </node>
        <node id="ATF4-individual" label="Tromelin Island" selectable="true">
        <hasNote></hasNote>
        </node>
        <node id="TUN-individual" label="Tunisia" selectable="true">
        <hasNote></hasNote>
        </node>
        <node id="TUR-individual" label="Turkey" selectable="true">
        <hasNote></hasNote>
        </node>
        <node id="TKM-individual" label="Turkmenistan" selectable="true">
        <hasNote></hasNote>
        </node>
        <node id="TCA-individual" label="Turks and Caicos Islands" selectable="true">
        <hasNote></hasNote>
        </node>
        <node id="TUV-individual" label="Tuvalu" selectable="true">
        <hasNote></hasNote>
        </node>
        <node id="UGA-individual" label="Uganda" selectable="true">
        <hasNote></hasNote>
        </node>
        <node id="UKR-individual" label="Ukraine" selectable="true">
        <hasNote></hasNote>
        </node>
        <node id="ARE-individual" label="United Arab Emirates" selectable="true">
        <hasNote></hasNote>
        </node>
        <node id="GBR-individual" label="United Kingdom" selectable="true">
        <hasNote></hasNote>
        </node>
        <node id="USA-individual" label="United States" selectable="true">
        <hasNote></hasNote>
        </node>
        <node id="UMI-individual" label="United States Minor Outlying Islands" selectable="true">
        <hasNote></hasNote>
        </node>
        <node id="URY-individual" label="Uruguay" selectable="true">
        <hasNote></hasNote>
        </node>
        <node id="UZB-individual" label="Uzbekistan" selectable="true">
        <hasNote></hasNote>
        </node>
        <node id="VUT-individual" label="Vanuatu" selectable="true">
        <hasNote></hasNote>
        </node>
        <node id="VAT-individual" label="Vatican City State" selectable="true">
        <hasNote></hasNote>
        </node>
        <node id="VEN-individual" label="Venezuela" selectable="true">
        <hasNote></hasNote>
        </node>
        <node id="VNM-individual" label="Viet Nam" selectable="true">
        <hasNote></hasNote>
        </node>
        <node id="VGB-individual" label="Virgin Islands" selectable="true">
        <hasNote></hasNote>
        </node>
        <node id="VIR-individual" label="Virgin Islands" selectable="true">
        <hasNote></hasNote>
        </node>
        <node id="WLF-individual" label="Wallis and Futuna" selectable="true">
        <hasNote></hasNote>
        </node>
        <node id="PSE2-individual" label="West Bank" selectable="true">
        <hasNote></hasNote>
        </node>
        <node id="ESH-individual" label="Western Sahara" selectable="true">
        <hasNote></hasNote>
        </node>
        <node id="YEM-individual" label="Yemen" selectable="true">
        <hasNote></hasNote>
        </node>
        <node id="ZMB-individual" label="Zambia" selectable="true">
        <hasNote></hasNote>
        </node>
        <node id="ZWE-individual" label="Zimbabwe" selectable="true">
        <hasNote></hasNote>
        </node>
      </isComposedBy>
    </node>
    <node id="Node3" label="Countries A-Z" selectable="false">
    <hasNote></hasNote>
      <isComposedBy>
        <node id="A" label="A" selectable="false">
        <hasNote></hasNote>
          <isComposedBy>
            <node id="AFG" label="Afghanistan" selectable="true">
            <hasNote></hasNote>
            </node>
            <node id="ALA" label="Åland Islands" selectable="true">
            <hasNote></hasNote>
            </node>
            <node id="ALB" label="Albania" selectable="true">
            <hasNote></hasNote>
            </node>
            <node id="DZA" label="Algeria" selectable="true">
            <hasNote></hasNote>
            </node>
            <node id="ASM" label="American Samoa" selectable="true">
            <hasNote></hasNote>
            </node>
            <node id="AND" label="Andorra" selectable="true">
            <hasNote></hasNote>
            </node>
            <node id="AGO" label="Angola" selectable="true">
            <hasNote></hasNote>
            </node>
            <node id="AIA" label="Anguilla" selectable="true">
            <hasNote></hasNote>
            </node>
            <node id="ATA" label="Antarctica" selectable="true">
            <hasNote></hasNote>
            </node>
            <node id="ATG" label="Antigua and Barbuda" selectable="true">
            <hasNote></hasNote>
            </node>
            <node id="ARG" label="Argentina" selectable="true">
            <hasNote></hasNote>
            </node>
            <node id="ARM" label="Armenia" selectable="true">
            <hasNote></hasNote>
            </node>
            <node id="ABW" label="Aruba" selectable="true">
            <hasNote></hasNote>
            </node>
            <node id="AUS" label="Australia" selectable="true">
            <hasNote></hasNote>
            </node>
            <node id="AUT" label="Austria" selectable="true">
            <hasNote></hasNote>
            </node>
            <node id="AZE" label="Azerbaijan" selectable="true">
            <hasNote></hasNote>
            </node>
          </isComposedBy>
        </node>
        <node id="B" label="B" selectable="false">
        <hasNote></hasNote>
          <isComposedBy>
            <node id="BHS" label="Bahamas" selectable="true">
            <hasNote></hasNote>
            </node>
            <node id="BHR" label="Bahrain" selectable="true">
            <hasNote></hasNote>
            </node>
            <node id="BGD" label="Bangladesh" selectable="true">
            <hasNote></hasNote>
            </node>
            <node id="BRB" label="Barbados" selectable="true">
            <hasNote></hasNote>
            </node>
            <node id="ATF1" label="Bassas da India" selectable="true">
            <hasNote></hasNote>
            </node>
            <node id="BLR" label="Belarus" selectable="true">
            <hasNote></hasNote>
            </node>
            <node id="BEL" label="Belgium" selectable="true">
            <hasNote></hasNote>
            </node>
            <node id="BLZ" label="Belize" selectable="true">
            <hasNote></hasNote>
            </node>
            <node id="BEN" label="Benin" selectable="true">
            <hasNote></hasNote>
            </node>
            <node id="BMU" label="Bermuda" selectable="true">
            <hasNote></hasNote>
            </node>
            <node id="BTN" label="Bhutan" selectable="true">
            <hasNote></hasNote>
            </node>
            <node id="BOL" label="Bolivia" selectable="true">
            <hasNote></hasNote>
            </node>
            <node id="BIH" label="Bosnia and Herzegovina" selectable="true">
            <hasNote></hasNote>
            </node>
            <node id="BWA" label="Botswana" selectable="true">
            <hasNote></hasNote>
            </node>
            <node id="BVT" label="Bouvet Island" selectable="true">
            <hasNote></hasNote>
            </node>
            <node id="BRA" label="Brazil" selectable="true">
            <hasNote></hasNote>
            </node>
            <node id="IOT" label="British Indian Ocean Territory" selectable="true">
            <hasNote></hasNote>
            </node>
            <node id="BRN" label="Brunei Darussalam" selectable="true">
            <hasNote></hasNote>
            </node>
            <node id="BGR" label="Bulgaria" selectable="true">
            <hasNote></hasNote>
            </node>
            <node id="BFA" label="Burkina Faso" selectable="true">
            <hasNote></hasNote>
            </node>
            <node id="BDI" label="Burundi" selectable="true">
            <hasNote></hasNote>
            </node>
            <node id="C" label="C" selectable="false">
            <hasNote></hasNote>
            </node>
            <node id="KHM" label="Cambodia" selectable="true">
            <hasNote></hasNote>
            </node>
            <node id="CMR" label="Cameroon" selectable="true">
            <hasNote></hasNote>
            </node>
            <node id="CAN" label="Canada" selectable="true">
            <hasNote></hasNote>
            </node>
            <node id="CPV" label="Cape Verde" selectable="true">
            <hasNote></hasNote>
            </node>
            <node id="CYM" label="Cayman Islands" selectable="true">
            <hasNote></hasNote>
            </node>
            <node id="CAF" label="Central African Republic" selectable="true">
            <hasNote></hasNote>
            </node>
            <node id="TCD" label="Chad" selectable="true">
            <hasNote></hasNote>
            </node>
            <node id="CHL" label="Chile" selectable="true">
            <hasNote></hasNote>
            </node>
            <node id="CHN" label="China" selectable="true">
            <hasNote></hasNote>
            </node>
            <node id="CXR" label="Christmas Island" selectable="true">
            <hasNote></hasNote>
            </node>
            <node id="FRAU" label="Clipperton" selectable="true">
            <hasNote></hasNote>
            </node>
            <node id="CCK" label="Cocos (Keeling) Islands" selectable="true">
            <hasNote></hasNote>
            </node>
            <node id="COL" label="Colombia" selectable="true">
            <hasNote></hasNote>
            </node>
            <node id="COM" label="Comoros" selectable="true">
            <hasNote></hasNote>
            </node>
            <node id="COD" label="Congo" selectable="true">
            <hasNote></hasNote>
            </node>
            <node id="COG" label="Congo" selectable="true">
            <hasNote></hasNote>
            </node>
            <node id="COK" label="Cook Islands" selectable="true">
            <hasNote></hasNote>
            </node>
            <node id="CRI" label="Costa Rica" selectable="true">
            <hasNote></hasNote>
            </node>
            <node id="HRV" label="Croatia" selectable="true">
            <hasNote></hasNote>
            </node>
            <node id="CUB" label="Cuba" selectable="true">
            <hasNote></hasNote>
            </node>
            <node id="CYP" label="Cyprus" selectable="true">
            <hasNote></hasNote>
            </node>
            <node id="CZE" label="Czech Republic" selectable="true">
            <hasNote></hasNote>
            </node>
            <node id="CIV" label="Côte d'Ivoire" selectable="true">
            <hasNote></hasNote>
            </node>
          </isComposedBy>
        </node>
        <node id="D" label="D" selectable="false">
        <hasNote></hasNote>
          <isComposedBy>
            <node id="DNK" label="Denmark" selectable="true">
            <hasNote></hasNote>
            </node>
            <node id="DJI" label="Djibouti" selectable="true">
            <hasNote></hasNote>
            </node>
            <node id="DMA" label="Dominica" selectable="true">
            <hasNote></hasNote>
            </node>
            <node id="DOM" label="Dominican Republic" selectable="true">
            <hasNote></hasNote>
            </node>
            <node id="ECU" label="Ecuador" selectable="true">
            <hasNote></hasNote>
            </node>
          </isComposedBy>
        </node>
        <node id="E" label="E" selectable="false">
        <hasNote></hasNote>
          <isComposedBy>
            <node id="EGY" label="Egypt" selectable="true">
            <hasNote></hasNote>
            </node>
            <node id="SLV" label="El Salvador" selectable="true">
            <hasNote></hasNote>
            </node>
            <node id="GNQ" label="Equatorial Guinea" selectable="true">
            <hasNote></hasNote>
            </node>
            <node id="ERI" label="Eritrea" selectable="true">
            <hasNote></hasNote>
            </node>
            <node id="EST" label="Estonia" selectable="true">
            <hasNote></hasNote>
            </node>
            <node id="ETH" label="Ethiopia" selectable="true">
            <hasNote></hasNote>
            </node>
          </isComposedBy>
        </node>
        <node id="F" label="F" selectable="false">
        <hasNote></hasNote>
          <isComposedBy>
            <node id="FLK" label="Falkland Islands (Malvinas)" selectable="true">
            <hasNote></hasNote>
            </node>
            <node id="FRO" label="Faroe Islands" selectable="true">
            <hasNote></hasNote>
            </node>
            <node id="FJI" label="Fiji" selectable="true">
            <hasNote></hasNote>
            </node>
            <node id="FIN" label="Finland" selectable="true">
            <hasNote></hasNote>
            </node>
            <node id="FRA" label="France" selectable="true">
            <hasNote></hasNote>
            </node>
            <node id="FXX" label="France (metropolitan)" selectable="true">
            <hasNote></hasNote>
            </node>
            <node id="GUF" label="French Guiana" selectable="true">
            <hasNote></hasNote>
            </node>
            <node id="PYF" label="French Polynesia" selectable="true">
            <hasNote></hasNote>
            </node>
            <node id="ATF" label="French Southern Territories" selectable="true">
            <hasNote></hasNote>
            </node>
          </isComposedBy>
        </node>
        <node id="G" label="G" selectable="false">
        <hasNote></hasNote>
          <isComposedBy>
            <node id="GAB" label="Gabon" selectable="true">
            <hasNote></hasNote>
            </node>
            <node id="GMB" label="Gambia" selectable="true">
            <hasNote></hasNote>
            </node>
            <node id="PSE1" label="Gaza Strip" selectable="true">
            <hasNote></hasNote>
            </node>
            <node id="GEO" label="Georgia" selectable="true">
            <hasNote></hasNote>
            </node>
            <node id="DEU" label="Germany" selectable="true">
            <hasNote></hasNote>
            </node>
            <node id="GHA" label="Ghana" selectable="true">
            <hasNote></hasNote>
            </node>
            <node id="GIB" label="Gibraltar" selectable="true">
            <hasNote></hasNote>
            </node>
            <node id="ATF2" label="Glorioso Islands" selectable="true">
            <hasNote></hasNote>
            </node>
            <node id="GRC" label="Greece" selectable="true">
            <hasNote></hasNote>
            </node>
            <node id="GRL" label="Greenland" selectable="true">
            <hasNote></hasNote>
            </node>
            <node id="GRD" label="Grenada" selectable="true">
            <hasNote></hasNote>
            </node>
            <node id="GLP" label="Guadeloupe" selectable="true">
            <hasNote></hasNote>
            </node>
            <node id="GUM" label="Guam" selectable="true">
            <hasNote></hasNote>
            </node>
            <node id="GTM" label="Guatemala" selectable="true">
            <hasNote></hasNote>
            </node>
            <node id="GGY" label="Guernsey" selectable="true">
            <hasNote></hasNote>
            </node>
            <node id="GIN" label="Guinea" selectable="true">
            <hasNote></hasNote>
            </node>
            <node id="GNB" label="Guinea-Bissau" selectable="true">
            <hasNote></hasNote>
            </node>
            <node id="GUY" label="Guyana" selectable="true">
            <hasNote></hasNote>
            </node>
          </isComposedBy>
        </node>
        <node id="H" label="H" selectable="false">
        <hasNote></hasNote>
          <isComposedBy>
            <node id="HTI" label="Haiti" selectable="true">
            <hasNote></hasNote>
            </node>
            <node id="HMD" label="Heard Island and McDonald Islands" selectable="true">
            <hasNote></hasNote>
            </node>
            <node id="HND" label="Honduras" selectable="true">
            <hasNote></hasNote>
            </node>
            <node id="HKG" label="Hong Kong" selectable="true">
            <hasNote></hasNote>
            </node>
            <node id="HUN" label="Hungary" selectable="true">
            <hasNote></hasNote>
            </node>
          </isComposedBy>
        </node>
        <node id="I" label="I" selectable="false">
        <hasNote></hasNote>
          <isComposedBy>
            <node id="ISL" label="Iceland" selectable="true">
            <hasNote></hasNote>
            </node>
            <node id="IND" label="India" selectable="true">
            <hasNote></hasNote>
            </node>
            <node id="IDN" label="Indonesia" selectable="true">
            <hasNote></hasNote>
            </node>
            <node id="IRN" label="Iran" selectable="true">
            <hasNote></hasNote>
            </node>
            <node id="IRQ" label="Iraq" selectable="true">
            <hasNote></hasNote>
            </node>
            <node id="IRL" label="Ireland" selectable="true">
            <hasNote></hasNote>
            </node>
            <node id="IMN" label="Isle of Man" selectable="true">
            <hasNote></hasNote>
            </node>
            <node id="ISR" label="Israel" selectable="true">
            <hasNote></hasNote>
            </node>
            <node id="ITA" label="Italy" selectable="true">
            <hasNote></hasNote>
            </node>
          </isComposedBy>
        </node>
        <node id="J" label="J" selectable="false">
        <hasNote></hasNote>
          <isComposedBy>
            <node id="JAM" label="Jamaica" selectable="true">
            <hasNote></hasNote>
            </node>
            <node id="JPN" label="Japan" selectable="true">
            <hasNote></hasNote>
            </node>
            <node id="JEY" label="Jersey" selectable="true">
            <hasNote></hasNote>
            </node>
            <node id="JOR" label="Jordan" selectable="true">
            <hasNote></hasNote>
            </node>
            <node id="ATF3" label="Juan de Nova Island" selectable="true">
            <hasNote></hasNote>
            </node>
          </isComposedBy>
        </node>
        <node id="K" label="K" selectable="false">
        <hasNote></hasNote>
          <isComposedBy>
            <node id="KAZ" label="Kazakhstan" selectable="true">
            <hasNote></hasNote>
            </node>
            <node id="KEN" label="Kenya" selectable="true">
            <hasNote></hasNote>
            </node>
            <node id="KIR" label="Kiribati" selectable="true">
            <hasNote></hasNote>
            </node>
            <node id="KOR" label="Korea" selectable="true">
            <hasNote></hasNote>
            </node>
            <node id="PRK" label="Korea" selectable="true">
            <hasNote></hasNote>
            </node>
            <node id="KWT" label="Kuwait" selectable="true">
            <hasNote></hasNote>
            </node>
            <node id="KGZ" label="Kyrgyzstan" selectable="true">
            <hasNote></hasNote>
            </node>
          </isComposedBy>
        </node>
        <node id="L" label="L" selectable="false">
        <hasNote></hasNote>
          <isComposedBy>
            <node id="LAO" label="Lao People's Democratic Republic" selectable="true">
            <hasNote></hasNote>
            </node>
            <node id="LVA" label="Latvia" selectable="true">
            <hasNote></hasNote>
            </node>
            <node id="LBN" label="Lebanon" selectable="true">
            <hasNote></hasNote>
            </node>
            <node id="LSO" label="Lesotho" selectable="true">
            <hasNote></hasNote>
            </node>
            <node id="LBR" label="Liberia" selectable="true">
            <hasNote></hasNote>
            </node>
            <node id="LBY" label="Libyan Arab Jamahiriya" selectable="true">
            <hasNote></hasNote>
            </node>
            <node id="LIE" label="Liechtenstein" selectable="true">
            <hasNote></hasNote>
            </node>
            <node id="LTU" label="Lithuania" selectable="true">
            <hasNote></hasNote>
            </node>
            <node id="LUX" label="Luxembourg" selectable="true">
            <hasNote></hasNote>
            </node>
          </isComposedBy>
        </node>
        <node id="M" label="M" selectable="false">
        <hasNote></hasNote>
          <isComposedBy>
            <node id="MAC" label="Macao" selectable="true">
            <hasNote></hasNote>
            </node>
            <node id="MKD" label="Macedonia" selectable="true">
            <hasNote></hasNote>
            </node>
            <node id="MDG" label="Madagascar" selectable="true">
            <hasNote></hasNote>
            </node>
            <node id="MWI" label="Malawi" selectable="true">
            <hasNote></hasNote>
            </node>
            <node id="MYS" label="Malaysia" selectable="true">
            <hasNote></hasNote>
            </node>
            <node id="MDV" label="Maldives" selectable="true">
            <hasNote></hasNote>
            </node>
            <node id="MLI" label="Mali" selectable="true">
            <hasNote></hasNote>
            </node>
            <node id="MLT" label="Malta" selectable="true">
            <hasNote></hasNote>
            </node>
            <node id="MHL" label="Marshall Islands" selectable="true">
            <hasNote></hasNote>
            </node>
            <node id="MTQ" label="Martinique" selectable="true">
            <hasNote></hasNote>
            </node>
            <node id="MRT" label="Mauritania" selectable="true">
            <hasNote></hasNote>
            </node>
            <node id="MUS" label="Mauritius" selectable="true">
            <hasNote></hasNote>
            </node>
            <node id="MYT" label="Mayotte" selectable="true">
            <hasNote></hasNote>
            </node>
            <node id="MEX" label="Mexico" selectable="true">
            <hasNote></hasNote>
            </node>
            <node id="FSM" label="Micronesia" selectable="true">
            <hasNote></hasNote>
            </node>
            <node id="MDA" label="Moldova" selectable="true">
            <hasNote></hasNote>
            </node>
            <node id="MCO" label="Monaco" selectable="true">
            <hasNote></hasNote>
            </node>
            <node id="MNG" label="Mongolia" selectable="true">
            <hasNote></hasNote>
            </node>
            <node id="MNE" label="Montenegro" selectable="true">
            <hasNote></hasNote>
            </node>
            <node id="MSR" label="Montserrat" selectable="true">
            <hasNote></hasNote>
            </node>
            <node id="MAR" label="Morocco" selectable="true">
            <hasNote></hasNote>
            </node>
            <node id="MOZ" label="Mozambique" selectable="true">
            <hasNote></hasNote>
            </node>
            <node id="MMR" label="Myanmar" selectable="true">
            <hasNote></hasNote>
            </node>
          </isComposedBy>
        </node>
        <node id="N" label="N" selectable="false">
        <hasNote></hasNote>
          <isComposedBy>
            <node id="NAM" label="Namibia" selectable="true">
            <hasNote></hasNote>
            </node>
            <node id="NRU" label="Nauru" selectable="true">
            <hasNote></hasNote>
            </node>
            <node id="NPL" label="Nepal" selectable="true">
            <hasNote></hasNote>
            </node>
            <node id="NLD" label="Netherlands" selectable="true">
            <hasNote></hasNote>
            </node>
            <node id="ANT" label="Netherlands Antilles" selectable="true">
            <hasNote></hasNote>
            </node>
            <node id="NCL" label="New Caledonia" selectable="true">
            <hasNote></hasNote>
            </node>
            <node id="NZL" label="New Zealand" selectable="true">
            <hasNote></hasNote>
            </node>
            <node id="NIC" label="Nicaragua" selectable="true">
            <hasNote></hasNote>
            </node>
            <node id="NER" label="Niger" selectable="true">
            <hasNote></hasNote>
            </node>
            <node id="NGA" label="Nigeria" selectable="true">
            <hasNote></hasNote>
            </node>
            <node id="NIU" label="Niue" selectable="true">
            <hasNote></hasNote>
            </node>
            <node id="NFK" label="Norfolk Island" selectable="true">
            <hasNote></hasNote>
            </node>
            <node id="MNP" label="Northern Mariana Islands" selectable="true">
            <hasNote></hasNote>
            </node>
            <node id="NOR" label="Norway" selectable="true">
            <hasNote></hasNote>
            </node>
          </isComposedBy>
        </node>
        <node id="O" label="O" selectable="false">
        <hasNote></hasNote>
          <isComposedBy>
            <node id="OMN" label="Oman" selectable="true">
            <hasNote></hasNote>
            </node>
          </isComposedBy>
        </node>
        <node id="P" label="P" selectable="false">
        <hasNote></hasNote>
          <isComposedBy>
            <node id="PAK" label="Pakistan" selectable="true">
            <hasNote></hasNote>
            </node>
            <node id="PLW" label="Palau" selectable="true">
            <hasNote></hasNote>
            </node>
            <node id="PSE" label="Palestinian Territory" selectable="true">
            <hasNote></hasNote>
            </node>
            <node id="PAN" label="Panama" selectable="true">
            <hasNote></hasNote>
            </node>
            <node id="PNG" label="Papua New Guinea" selectable="true">
            <hasNote></hasNote>
            </node>
            <node id="PRY" label="Paraguay" selectable="true">
            <hasNote></hasNote>
            </node>
            <node id="PER" label="Peru" selectable="true">
            <hasNote></hasNote>
            </node>
            <node id="PHL" label="Philippines" selectable="true">
            <hasNote></hasNote>
            </node>
            <node id="PCN" label="Pitcairn" selectable="true">
            <hasNote></hasNote>
            </node>
            <node id="POL" label="Poland" selectable="true">
            <hasNote></hasNote>
            </node>
            <node id="PRT" label="Portugal" selectable="true">
            <hasNote></hasNote>
            </node>
            <node id="PRI" label="Puerto Rico" selectable="true">
            <hasNote></hasNote>
            </node>
          </isComposedBy>
        </node>
        <node id="Q" label="Q" selectable="false">
        <hasNote></hasNote>
          <isComposedBy>
            <node id="QAT" label="Qatar" selectable="true">
            <hasNote></hasNote>
            </node>
          </isComposedBy>
        </node>
        <node id="R" label="R" selectable="false">
        <hasNote></hasNote>
          <isComposedBy>
            <node id="ROU" label="Romania" selectable="true">
            <hasNote></hasNote>
            </node>
            <node id="RUS" label="Russian Federation" selectable="true">
            <hasNote></hasNote>
            </node>
            <node id="RWA" label="Rwanda" selectable="true">
            <hasNote></hasNote>
            </node>
            <node id="REU" label="Réunion" selectable="true">
            <hasNote></hasNote>
            </node>
          </isComposedBy>
        </node>
        <node id="S" label="S" selectable="false">
        <hasNote></hasNote>
          <isComposedBy>
            <node id="BLM" label="Saint Barthélemy" selectable="true">
            <hasNote></hasNote>
            </node>
            <node id="SHN" label="Saint Helena" selectable="true">
            <hasNote></hasNote>
            </node>
            <node id="KNA" label="Saint Kitts and Nevis" selectable="true">
            <hasNote></hasNote>
            </node>
            <node id="LCA" label="Saint Lucia" selectable="true">
            <hasNote></hasNote>
            </node>
            <node id="MAF" label="Saint Martin (French part)" selectable="true">
            <hasNote></hasNote>
            </node>
            <node id="SPM" label="Saint Pierre and Miquelon" selectable="true">
            <hasNote></hasNote>
            </node>
            <node id="VCT" label="Saint Vincent and the Grenadines" selectable="true">
            <hasNote></hasNote>
            </node>
            <node id="WSM" label="Samoa" selectable="true">
            <hasNote></hasNote>
            </node>
            <node id="SMR" label="San Marino" selectable="true">
            <hasNote></hasNote>
            </node>
            <node id="STP" label="Sao Tome and Principe" selectable="true">
            <hasNote></hasNote>
            </node>
            <node id="SAU" label="Saudi Arabia" selectable="true">
            <hasNote></hasNote>
            </node>
            <node id="SEN" label="Senegal" selectable="true">
            <hasNote></hasNote>
            </node>
            <node id="SRB" label="Serbia" selectable="true">
            <hasNote></hasNote>
            </node>
            <node id="SYC" label="Seychelles" selectable="true">
            <hasNote></hasNote>
            </node>
            <node id="SLE" label="Sierra Leone" selectable="true">
            <hasNote></hasNote>
            </node>
            <node id="SGP" label="Singapore" selectable="true">
            <hasNote></hasNote>
            </node>
            <node id="SVK" label="Slovakia" selectable="true">
            <hasNote></hasNote>
            </node>
            <node id="SVN" label="Slovenia" selectable="true">
            <hasNote></hasNote>
            </node>
            <node id="SLB" label="Solomon Islands" selectable="true">
            <hasNote></hasNote>
            </node>
            <node id="SOM" label="Somalia" selectable="true">
            <hasNote></hasNote>
            </node>
            <node id="ZAF" label="South Africa" selectable="true">
            <hasNote></hasNote>
            </node>
            <node id="SGS" label="South Georgia and the South Sandwich Islands" selectable="true">
            <hasNote></hasNote>
            </node>
            <node id="SSD" label="South Sudan" selectable="true">
            <hasNote></hasNote>
            </node>
            <node id="ESP" label="Spain" selectable="true">
            <hasNote></hasNote>
            </node>
            <node id="LKA" label="Sri Lanka" selectable="true">
            <hasNote></hasNote>
            </node>
            <node id="SDN" label="Sudan" selectable="true">
            <hasNote></hasNote>
            </node>
            <node id="SUR" label="Suriname" selectable="true">
            <hasNote></hasNote>
            </node>
            <node id="SJM" label="Svalbard and Jan Mayen" selectable="true">
            <hasNote></hasNote>
            </node>
            <node id="SWZ" label="Swaziland" selectable="true">
            <hasNote></hasNote>
            </node>
            <node id="SWE" label="Sweden" selectable="true">
            <hasNote></hasNote>
            </node>
            <node id="CHE" label="Switzerland" selectable="true">
            <hasNote></hasNote>
            </node>
            <node id="SYR" label="Syrian Arab Republic" selectable="true">
            <hasNote></hasNote>
            </node>
          </isComposedBy>
        </node>
        <node id="T" label="T" selectable="false">
        <hasNote></hasNote>
          <isComposedBy>
            <node id="TWN" label="Taiwan" selectable="true">
            <hasNote></hasNote>
            </node>
            <node id="TJK" label="Tajikistan" selectable="true">
            <hasNote></hasNote>
            </node>
            <node id="TZA" label="Tanzania" selectable="true">
            <hasNote></hasNote>
            </node>
            <node id="THA" label="Thailand" selectable="true">
            <hasNote></hasNote>
            </node>
            <node id="TLS" label="Timor-Leste" selectable="true">
            <hasNote></hasNote>
            </node>
            <node id="TGO" label="Togo" selectable="true">
            <hasNote></hasNote>
            </node>
            <node id="TKL" label="Tokelau" selectable="true">
            <hasNote></hasNote>
            </node>
            <node id="TON" label="Tonga" selectable="true">
            <hasNote></hasNote>
            </node>
            <node id="TTO" label="Trinidad and Tobago" selectable="true">
            <hasNote></hasNote>
            </node>
            <node id="ATF4" label="Tromelin Island" selectable="true">
            <hasNote></hasNote>
            </node>
            <node id="TUN" label="Tunisia" selectable="true">
            <hasNote></hasNote>
            </node>
            <node id="TUR" label="Turkey" selectable="true">
            <hasNote></hasNote>
            </node>
            <node id="TKM" label="Turkmenistan" selectable="true">
            <hasNote></hasNote>
            </node>
            <node id="TCA" label="Turks and Caicos Islands" selectable="true">
            <hasNote></hasNote>
            </node>
            <node id="TUV" label="Tuvalu" selectable="true">
            <hasNote></hasNote>
            </node>
          </isComposedBy>
        </node>
        <node id="U" label="U" selectable="false">
        <hasNote></hasNote>
          <isComposedBy>
            <node id="UGA" label="Uganda" selectable="true">
            <hasNote></hasNote>
            </node>
            <node id="UKR" label="Ukraine" selectable="true">
            <hasNote></hasNote>
            </node>
            <node id="ARE" label="United Arab Emirates" selectable="true">
            <hasNote></hasNote>
            </node>
            <node id="GBR" label="United Kingdom" selectable="true">
            <hasNote></hasNote>
            </node>
            <node id="USA" label="United States" selectable="true">
            <hasNote></hasNote>
            </node>
            <node id="UMI" label="United States Minor Outlying Islands" selectable="true">
            <hasNote></hasNote>
            </node>
            <node id="URY" label="Uruguay" selectable="true">
            <hasNote></hasNote>
            </node>
            <node id="UZB" label="Uzbekistan" selectable="true">
            <hasNote></hasNote>
            </node>
          </isComposedBy>
        </node>
        <node id="V" label="V" selectable="false">
        <hasNote></hasNote>
          <isComposedBy>
            <node id="VUT" label="Vanuatu" selectable="true">
            <hasNote></hasNote>
            </node>
            <node id="VAT" label="Vatican City State" selectable="true">
            <hasNote></hasNote>
            </node>
            <node id="VEN" label="Venezuela" selectable="true">
            <hasNote></hasNote>
            </node>
            <node id="VNM" label="Viet Nam" selectable="true">
            <hasNote></hasNote>
            </node>
            <node id="VGB" label="Virgin Islands" selectable="true">
            <hasNote></hasNote>
            </node>
            <node id="VIR" label="Virgin Islands" selectable="true">
            <hasNote></hasNote>
            </node>
          </isComposedBy>
        </node>
        <node id="W" label="W" selectable="false">
        <hasNote></hasNote>
          <isComposedBy>
            <node id="WLF" label="Wallis and Futuna" selectable="true">
            <hasNote></hasNote>
            </node>
            <node id="PSE2" label="West Bank" selectable="true">
            <hasNote></hasNote>
            </node>
            <node id="ESH" label="Western Sahara" selectable="true">
            <hasNote></hasNote>
            </node>
          </isComposedBy>
        </node>
        <node id="Y" label="Y" selectable="false">
        <hasNote></hasNote>
          <isComposedBy>
            <node id="YEM" label="Yemen" selectable="true">
            <hasNote></hasNote>
            </node>
          </isComposedBy>
        </node>
        <node id="Z" label="Z" selectable="false">
        <hasNote></hasNote>
          <isComposedBy>
            <node id="ZMB" label="Zambia" selectable="true">
            <hasNote></hasNote>
            </node>
            <node id="ZWE" label="Zimbabwe" selectable="true">
            <hasNote></hasNote>
            </node>
          </isComposedBy>
        </node>
      </isComposedBy>
    </node>
  </isComposedBy>
</node>
